[



    {
        "website": "http://atlas.co", 
        "description": "Atlas Recall gives you a photographic memory for your digital life. Easy search for any email, file, cloud service, webpage and so much more with a single search.  Recall was designed to complement the apps you already love, making you more productive with minimal effort.", 
        "founded": 2015, 
        "street": null, 
        "specialities": null, 
        "size": "11-50 employees", 
        "city": null, 
        "zip": null, 
        "url": "https://www.linkedin.com/company/atlas-informatics", 
        "country": null, 
        "industry": "Computer Software", 
        "state": null, 
        "company_name": "Atlas Informatics", 
        "follower_count": 251, 
        "type": "Privately Held"
    }
]